jsonplate/__init__.py
jsonplate/errors.py
jsonplate/jsonplate.py
jsonplate/lexer.py
jsonplate/parser.py
jsonplate/templater.py
jsonplate-0.0.1.dist-info/licenses/LICENSE
jsonplate-0.0.1.dist-info/METADATA
jsonplate-0.0.1.dist-info/WHEEL
jsonplate-0.0.1.dist-info/top_level.txt
jsonplate-0.0.1.dist-info/RECORD
