Metadata-Version: 2.4
Name: jsonplate
Version: 0.0.1
Summary: A Python package to parse JSON and JSON templates
Author-email: Francisco Rodrigues <francisco.rodrigues0908@gmail.com>
License: MIT No Attribution
License-File: LICENSE
Dynamic: license-file
